pyFRF.py
pyfrf-1.1.4.dist-info/METADATA
pyfrf-1.1.4.dist-info/WHEEL
pyfrf-1.1.4.dist-info/licenses/LICENSE
pyfrf-1.1.4.dist-info/RECORD
