Metadata-Version: 2.4
Name: pyFRF
Version: 1.1.4
Summary: Frequency response function as used in structural dynamics.
Project-URL: homepage, https://github.com/ladisk/pyFRF
Project-URL: documentation, https://pyfrf.readthedocs.io/en/latest/
Project-URL: source, https://github.com/ladisk/pyFRF
Author-email: "Janko Slavič, Luka Novak, Martin Česnik, et al." <janko.slavic@fs.uni-lj.si>
Maintainer-email: "Janko Slavič, Luka Novak, Martin Česnik, et al." <janko.slavic@fs.uni-lj.si>
License-Expression: MIT
License-File: LICENSE
Keywords: FRF,MIMO,ODS,SIMO
Classifier: Development Status :: 5 - Production/Stable
Classifier: Intended Audience :: Developers
Classifier: License :: OSI Approved :: MIT License
Classifier: Programming Language :: Python :: 3.10
Classifier: Topic :: Scientific/Engineering
Requires-Python: >=3.10
Requires-Dist: colorama
Requires-Dist: lvm-read
Requires-Dist: matplotlib
Requires-Dist: numpy>=1.11.0
Requires-Dist: py
Requires-Dist: pyexsi
Requires-Dist: scipy>=1.2.0
Requires-Dist: sdypy-sep005
Provides-Extra: dev
Requires-Dist: jupyter; extra == 'dev'
Requires-Dist: nbsphinx; extra == 'dev'
Requires-Dist: nbsphinx-link; extra == 'dev'
Requires-Dist: pytest; extra == 'dev'
Requires-Dist: sphinx; extra == 'dev'
Requires-Dist: sphinx-book-theme; extra == 'dev'
Requires-Dist: sphinx-rtd-theme; extra == 'dev'
Requires-Dist: twine; extra == 'dev'
Requires-Dist: wheel; extra == 'dev'
